dader/__init__.py
dader/__version__.py
dader/param.py
dader/data/__init__.py
dader/data/_utils.py
dader/data/dataset.py
dader/data/process.py
dader/metrics/__init__.py
dader/metrics/coral.py
dader/metrics/js.py
dader/metrics/mmd.py
dader/model/__init__.py
dader/model/_utils.py
dader/model/alignment.py
dader/model/extractor.py
dader/model/matcher.py
dader/model/model.py
dader/runner/__init__.py
dader/runner/adapt_coral.py
dader/runner/adapt_ed.py
dader/runner/adapt_grl.py
dader/runner/adapt_invgan.py
dader/runner/adapt_invgan_kd.py
dader/runner/adapt_mmd.py
dader/runner/evaluate.py
dader/runner/pretrain.py
dader-0.0.4.dist-info/LICENSE
dader-0.0.4.dist-info/METADATA
dader-0.0.4.dist-info/WHEEL
dader-0.0.4.dist-info/top_level.txt
dader-0.0.4.dist-info/RECORD
